Metadata-Version: 2.1
Name: igwn-alert-overseer
Version: 0.7.0
Summary: igwn-alert Overseer Server and Client Tools
Author: Alexander Pace
Author-email: alexander.pace@ligo.org
License: GPLv3
License-File: COPYING
Requires-Dist: twisted
Requires-Dist: tornado>=6.2
Requires-Dist: igwn-alert>=0.5.0
